{"pageProps":{"info":{"data":{"aliasName":"月が導く異世界道中,Tsuki ga michibiku isekai-dôchû","areaList":[{"id":44,"name":"Japan"}],"areaNameList":["Japan"],"category":1,"collect":false,"contentTagResourceList":[],"coverHorizontalUrl":"https://img.netpop.app/cover/20220104/1641263069497_a0949b92e5bbfbdd431615b66a498851ciPDoPMqd3icCBHsIlhIb3UyOd2.jpg","coverHorizontalUrlJson":"","coverVerticalUrl":"https://img.netpop.app/cover/20220104/1641263065502_206d0fce6afdcf84c4a1d257bece2099oGTihBVxHROSWa1WJnireCbl0KQ.jpg","drameTypeVo":{"drameName":"Anime","drameType":"COMIC"},"episodeCount":12,"episodeRoomListVo":{"category":0,"episodeId":"","episodeName":"","number":0,"roomId":"","seasonID":"","seasonName":""},"episodeVo":12,"id":"10346","introduction":"Makoto Misumi is an ordinary high school boy summoned to an alternate world as a brave warrior. Unfortunately, the goddess of the world said with disdain, \"Your face is ugly,\" stripped him of his title, and banished him to the outermost fringes of the wilderness. While wandering the wilderness, Makoto encountered dragons, spiders, orcs, dwarves, and all sorts of other non-human species. Due to differences in the environment from his home world, Makoto now exhibits extraordinary powers in magic and combat. Thus, he survives on this world while dealing with various encounters. The curtain rises on the alternate-world social reform fantasy of a boy forsaken by gods and humans.","likeList":[{"areaList":[{"id":44,"name":"Japan"}],"areaNameList":["Japan"],"category":1,"coverHorizontalUrl":"https://img.netpop.app/cover/20220104/1641266718889_f70493c843553370427a061f86bdb522xOi6lRbJh3fBFur8QuxTyGzOqiH.jpg","coverVerticalUrl":"https://img.netpop.app/cover/20220104/1641266714349_39775e704a12ba284b2c536109d7e330nGuTtEc5q3pO6Kl2Pmszc9IwEe.jpg","drameTypeVo":{"drameName":"Anime","drameType":"COMIC"},"id":"10350","name":"Battle Game in 5 Seconds","score":6.8,"tagList":[{"id":1,"name":"Action"},{"id":2,"name":"Adventure"},{"id":3,"name":"Anime"},{"id":8,"name":"Drama"},{"id":10,"name":"Fantasy"}],"tagNameList":["Action","Adventure","Anime","Drama","Fantasy"],"upImgUrl":"https://img.rr.tv/head/20170820/o_1503170995439.jpg","upName":"Christian Zimmerman","year":2021},{"areaList":[{"id":44,"name":"Japan"}],"areaNameList":["Japan"],"category":1,"coverHorizontalUrl":"https://img.netpop.app/cover/20211231/1640930113420_b65f3aea91561b8fe225117381f3a277hqalGitZD9f2bOlmRUBd5MoIQqH.jpg","coverVerticalUrl":"https://img.netpop.app/cover/20211231/1640930108801_c080abd62edacbc7b3eadfc7b30cb6cezXN3jur7j2R6zw9ed3jm0rqYtzu.jpg","drameTypeVo":{"drameName":"Anime","drameType":"COMIC"},"id":"10272","name":"The Honor at Magic High School","score":6.5,"tagList":[{"id":3,"name":"Anime"}],"tagNameList":["Anime"],"upImgUrl":"https://img.rr.tv/head/20171109/o_1510220537871.png","upName":"Herman William","year":2021},{"areaList":[{"id":44,"name":"Japan"}],"areaNameList":["Japan"],"category":1,"coverHorizontalUrl":"https://img.netpop.app/cover/20220104/1641284859583_1b3ec90b27dc283038cde6debd969b3fODcHQvZ6pkGMK2fsjib03qMq1q.jpg","coverVerticalUrl":"https://img.netpop.app/cover/20220104/1641284855326_a10829874a06ad2d2806908b5aed3cdftG92mLqwXdByHNhGp8yOxIc1BjE.jpg","drameTypeVo":{"drameName":"Anime","drameType":"COMIC"},"id":"10368","name":"Re-Main","score":7.3,"tagList":[{"id":3,"name":"Anime"},{"id":21,"name":"Sports"}],"tagNameList":["Anime","Sports"],"upImgUrl":"https://img.rr.tv/head/20170714/o_1500004854325.png","upName":"Clark Betsy","year":2021},{"areaList":[{"id":44,"name":"Japan"}],"areaNameList":["Japan"],"category":1,"coverHorizontalUrl":"https://img.netpop.app/cover/20211229/1640755927687_c6614e4cb2901157b6766e3be590540b慎勇 横.jpg","coverVerticalUrl":"https://img.netpop.app/cover/20211229/1640755925202_5126b6fcaac7b0bb0a3e6576db0684e9慎勇 竖.jpg","drameTypeVo":{"drameName":"Anime","drameType":"COMIC"},"id":"10062","name":"Cautious Hero: The Hero Is Overpowered but Overly Cautious","score":7.4,"tagList":[{"id":1,"name":"Action"},{"id":2,"name":"Adventure"},{"id":3,"name":"Anime"},{"id":5,"name":"Comedy"},{"id":8,"name":"Drama"},{"id":10,"name":"Fantasy"}],"tagNameList":["Action","Adventure","Anime","Comedy","Drama","Fantasy"],"upImgUrl":"http://img.rr.tv/head/20200715/o_006s5TrDgw1f43ip1wzhmj30u00u0gpi.jpg","upName":"Jonas Job","year":2019},{"areaList":[{"id":44,"name":"Japan"}],"areaNameList":["Japan"],"category":1,"coverHorizontalUrl":"https://img.netpop.app/cover/20211230/1640846750015_f04c8d9f3192755ce1830465a5d019d6gO0Nhi2XFbKqzaxx7za5SSoRcLi.jpg","coverVerticalUrl":"https://img.netpop.app/cover/20211230/1640846746546_455194087c65c6e8242145039a6624e02R73KniOaH3rUm7DhteM2Xhw00c.jpg","drameTypeVo":{"drameName":"Anime","drameType":"COMIC"},"id":"10203","name":"Interspecies Reviewers","score":7.5,"tagList":[{"id":3,"name":"Anime"}],"tagNameList":["Anime"],"upImgUrl":"http://img.rr.tv/head/20200715/o_005R1mzTly1gf65seikj6j30u0140wsu.jpg","upName":"Rock Meg","year":2020},{"areaList":[{"id":44,"name":"Japan"}],"areaNameList":["Japan"],"category":1,"coverHorizontalUrl":"https://img.netpop.app/cover/20211229/1640748130301_c9f47501a346c32f32400fdc9eb1f375赛马娘 横.jpg","coverVerticalUrl":"https://img.netpop.app/cover/20220207/1644215068752_8cf63c35c24c6c37ddd3bd86ee1d738c赛马娘 第二季10050竖版.png","drameTypeVo":{"drameName":"Anime","drameType":"COMIC"},"id":"10050","name":"Uma Musume: Pretty Derby Season 2","score":7.1,"tagList":[{"id":3,"name":"Anime"},{"id":21,"name":"Sports"}],"tagNameList":["Anime","Sports"],"upImgUrl":"http://img.rr.tv/head/20200715/o_006hyka7ly1gg2dz7ewpkj30sg0sg188.jpg","upName":"Hazel Norton","year":2021},{"areaList":[{"id":44,"name":"Japan"}],"areaNameList":["Japan"],"category":1,"coverHorizontalUrl":"https://img.netpop.app/cover/20211230/1640846421494_c0af2aab3c2bbf9525f5a65602c263798fsV0aqSHQlbyvZlWyynruat0MP.jpg","coverVerticalUrl":"https://img.netpop.app/cover/20211230/1640846416157_909363f719dff49e987b27abfa6182ecyyPvh32LQS1zWFTBkynZ6aVAsHD.jpg","drameTypeVo":{"drameName":"Anime","drameType":"COMIC"},"id":"10201","name":"Higurashi: When They Cry - Sotsu","score":6.8,"tagList":[{"id":3,"name":"Anime"}],"tagNameList":["Anime"],"upImgUrl":"https://img.rr.tv/head/20170705/o_1499234799789.png","upName":"Diana Malachi","year":2021},{"areaList":[{"id":44,"name":"Japan"}],"areaNameList":["Japan"],"category":1,"coverHorizontalUrl":"https://img.netpop.app/cover/20220207/1644228830270_3ef5c3a12af6c1b4563b254df79f9be7死神少爷与黑女仆10321横版.png","coverVerticalUrl":"https://img.netpop.app/cover/20220207/1644228823725_719bec51ca7a0dd62fed1b313d2cd4fe死神少爷与黑女仆10321竖版.png","drameTypeVo":{"drameName":"Anime","drameType":"COMIC"},"id":"10321","name":"The Duke of Death and His Maid","score":7.1,"tagList":[{"id":3,"name":"Anime"},{"id":8,"name":"Drama"},{"id":10,"name":"Fantasy"}],"tagNameList":["Anime","Drama","Fantasy"],"upImgUrl":"https://img.rr.tv/head/20170406/o_1491463053271.jpg","upName":"Venus","year":2021},{"areaList":[{"id":44,"name":"Japan"}],"areaNameList":["Japan"],"category":1,"coverHorizontalUrl":"https://img.netpop.app/cover/20220104/1641268787119_eb57d9d4aeeb5aa9de3cb59beeb843c82OUwaSJ5qonI7WKpYFHWnItF9mC.jpg","coverVerticalUrl":"https://img.netpop.app/cover/20220104/1641268782328_9ada0520ac43980184bd7c6e6ed4dabdk71BPHfda6jQS350IoJSkKkGm8A.jpg","drameTypeVo":{"drameName":"Anime","drameType":"COMIC"},"id":"10352","name":"The Dungeon of Black Company","score":6.8,"tagList":[{"id":3,"name":"Anime"},{"id":5,"name":"Comedy"},{"id":8,"name":"Drama"},{"id":10,"name":"Fantasy"}],"tagNameList":["Anime","Comedy","Drama","Fantasy"],"upImgUrl":"http://img.rr.tv/head/20191120/o_1574245535850.jpeg","upName":"Lorraine Meredith","year":2021},{"areaList":[{"id":44,"name":"Japan"}],"areaNameList":["Japan"],"category":1,"coverHorizontalUrl":"https://img.netpop.app/cover/20220105/1641350152305_4b93065a17e75a5c5894bd0aec76d15d1E1n0ZMsgvGHBnMLggaZCe7IVrR.jpg","coverVerticalUrl":"https://img.netpop.app/cover/20220105/1641350220287_2fd57f03bdc1a22d799f1cf22b54587cmJ7t9wyD43H32E9Sv22mMrVmkLo.jpg","drameTypeVo":{"drameName":"Anime","drameType":"COMIC"},"id":"10382","name":"Night Head 2041","score":6.9,"tagList":[{"id":3,"name":"Anime"},{"id":19,"name":"Sci-Fi"}],"tagNameList":["Anime","Sci-Fi"],"upImgUrl":"https://img.rr.tv/head/20170110/o_1484027123321.jpg","upName":"Moses Tours","year":2021}],"name":"Tsukimichi: Moonlit Fantasy","nameJson":"","refList":[],"reserved":false,"score":7.6,"seriesNo":null,"showSetName":false,"starList":[],"tagList":[{"id":3,"name":"Anime"}],"tagNameList":["Anime"],"translateType":1,"upInfo":{"upId":100658,"upImgUrl":"http://img.rr.tv/head/20200519/o_1589885506544.jpg","upName":"Kevin Surrey"},"updateInfo":{"updatePeriod":"","updateStatus":4},"year":2021},"sources":[{"quality":1080,"url":"https://ali-cdn-play.loklok.tv/3613fe2612634d0db162801ef9dc9b73/3cfb1682800f42528d1a00de126fd2af-22266f18b2c3e5862f1a65b5d742fac2-hd.m3u8?auth_key=1665196240-8f49398df24144d9a833b6132f9d6413-0-2fc25d1203892e2fc45dc5abd7db9a4f"},{"quality":720,"url":"https://ali-cdn-play.loklok.tv/3613fe2612634d0db162801ef9dc9b73/3cfb1682800f42528d1a00de126fd2af-46be60d91a0ca7e4422e047c18ae08d6-sd.m3u8?auth_key=1665196240-85c7a4ab81674a8fa319bcac66bca1d9-0-743b258c0b0c9f557475b19f55a9292a"},{"quality":540,"url":"https://ali-cdn-play.loklok.tv/3613fe2612634d0db162801ef9dc9b73/3cfb1682800f42528d1a00de126fd2af-afd15c66bc5f5a9be908e9243568472c-ld.m3u8?auth_key=1665196240-cfb36eeb40f344458290d63f5564219d-0-61638dee415e38045f1a974b8cddd9eb"}],"subtitles":[{"language":"Tiếng Việt","url":"https://subtitles.netpop.app/subtitles/20220104/1641264774006_Tsukimichi -Moonlit Fantasy--ep-E1-vi.srt","lang":"vi"},{"language":"English","url":"https://subtitles.netpop.app/subtitles/20220104/1641264762530_Tsukimichi -Moonlit Fantasy--ep-E1-en.srt","lang":"en"},{"language":"Bahasa Indonesia","url":"https://subtitles.netpop.app/subtitles/20220104/1641264766569_Tsukimichi -Moonlit Fantasy--ep-E1-id.srt","lang":"in_ID"},{"language":"Bahasa Melayu (Auto)","url":"https://subtitles.netpop.app/subtitles/20220112/1641981703477_ms_1641264762530_Tsukimichi -Moonlit Fantasy--ep-E1-en.srt","lang":"ms"},{"language":"ภาษาไทย","url":"https://subtitles.netpop.app/subtitles/20220104/1641264771111_Tsukimichi -Moonlit Fantasy--ep-E1-th.srt","lang":"th"},{"language":"简体中文 (Auto)","url":"https://subtitles.netpop.app/subtitles/20220112/1641981703476_zh_CN_1641264762530_Tsukimichi -Moonlit Fantasy--ep-E1-en.srt","lang":"zh_CN"},{"language":"繁体中文 (Auto)","url":"https://subtitles.netpop.app/subtitles/20220112/1641981703478_zh_TW_1641264762530_Tsukimichi -Moonlit Fantasy--ep-E1-en.srt","lang":"zh_TW"},{"language":"عربي","url":"https://subtitles.netpop.app/subtitles/20220104/1641264779414_Tsukimichi -Moonlit Fantasy--ep-E01-ar.srt","lang":"ar"},{"language":"فارسی","url":"https://subtitles.netpop.app/subtitles/20220104/1641264782976_Tsukimichi -Moonlit Fantasy--ep-E01-per.srt","lang":"fa"},{"language":"português (Auto)","url":"https://subtitles.netpop.app/subtitles/20220112/1641981703481_pt_1641264762530_Tsukimichi -Moonlit Fantasy--ep-E1-en.srt","lang":"pt"},{"language":"Türk (Auto)","url":"https://subtitles.netpop.app/subtitles/20220112/1641981703482_tr_1641264762530_Tsukimichi -Moonlit Fantasy--ep-E1-en.srt","lang":"tr"},{"language":"français (Auto)","url":"https://subtitles.netpop.app/subtitles/20220112/1641981703809_fr_1641264762530_Tsukimichi -Moonlit Fantasy--ep-E1-en.srt","lang":"fr"}]}},"__N_SSG":true}