{"pageProps":{"info":{"data":{"aliasName":"The Lord of the Rings: The Rings of Power / The Lord of the Rings","areaList":[{"id":61,"name":"America"}],"areaNameList":["America"],"category":1,"collect":false,"contentTagResourceList":[],"coverHorizontalUrl":"https://img.netpop.app/cover/20220721/1658390940330_90704ee86e15586acde996db6bb78bb1uVukvj5r9jEMva78IfaGWMNwGe.jpg","coverHorizontalUrlJson":"","coverVerticalUrl":"https://img.netpop.app/cover/20220916/1663310931648_6c8eb57c9eb0b68bf616001bb0f559e557qMrgNoh72wF5sVEDrtMlRk7D.jpg","drameTypeVo":{"drameName":"drama","drameType":"TV"},"episodeCount":8,"episodeRoomListVo":{"category":0,"episodeId":"","episodeName":"","number":0,"roomId":"","seasonID":"","seasonName":""},"episodeVo":7,"id":"22483","introduction":"This epic drama is set thousands of years before the events of J.R.R. Tolkien’s The Hobbit and The Lord of the Rings, and will take viewers back to an era in which great powers were forged, kingdoms rose to glory and fell to ruin, unlikely heroes were tested, hope hung by the finest of threads, and the greatest villain that ever flowed from Tolkien’s pen threatened to cover all the world in darkness. Beginning in a time of relative peace, the series follows an ensemble cast of characters, both familiar and new, as they confront the long-feared re-emergence of evil to Middle-earth. From the darkest depths of the Misty Mountains, to the majestic forests of the elf-capital of Lindon, to the breathtaking island kingdom of Númenor, to the furthest reaches of the map, these kingdoms and characters will carve out legacies that live on long after they are gone.","likeList":[{"areaList":[{"id":32,"name":"China"}],"areaNameList":["China"],"category":1,"coverHorizontalUrl":"https://img.netpop.app/cover/20210813/o_1628857147316.jpg","coverVerticalUrl":"https://img.netpop.app/cover/20220823/1661220399981_6bb9809635cec3f051f50b7ee1e27de9我的绝密生涯.png","drameTypeVo":{"drameName":"drama","drameType":"TV"},"id":"1","name":"My top secret career","score":6.2,"tagList":[{"id":8,"name":"Drama"},{"id":16,"name":"Suspense"}],"tagNameList":["Drama","Suspense"],"upImgUrl":"http://img.rr.tv/head/20191115/o_1573805198870.jpeg","upName":"Sid Hill","year":2014},{"areaList":[{"id":61,"name":"America"}],"areaNameList":["America"],"category":1,"coverHorizontalUrl":"https://img.netpop.app/cover/20211111/1636630374844_9ae3d71605001bb49f695220f8bbf46f星星光束 第三季.png","coverVerticalUrl":"https://img.netpop.app/cover/20211111/1636630349068_efaf92851a4e7c46e36db0022bfb4ba9星星光束 第三季.png","drameTypeVo":{"drameName":"drama","drameType":"TV"},"id":"1005","name":"StarBeam Season 3","score":6.9,"tagList":[{"id":1,"name":"Action"},{"id":2,"name":"Adventure"},{"id":3,"name":"Anime"},{"id":5,"name":"Comedy"},{"id":9,"name":"Family"},{"id":10,"name":"Fantasy"},{"id":19,"name":"Sci-Fi"}],"tagNameList":["Action","Adventure","Anime","Comedy","Family","Fantasy","Sci-Fi"],"upImgUrl":"http://img.rr.tv/head/20190614/o_1560477637455.gif","upName":"Truda Marcus","year":2021},{"areaList":[{"id":53,"name":"South Korea"}],"areaNameList":["South Korea"],"category":1,"coverHorizontalUrl":"https://img.netpop.app/cover/20211229/1640765253853_919e1d67fbc808ffa2820003d37709f83kzPeAT0XuTkoJn77WWlbpOtOGs.jpg","coverVerticalUrl":"https://img.netpop.app/cover/20211229/1640765249334_25ac0b683f2ec2bd4c60a11ce065a17dugLwOOv9k6NG0XL2IX06RiqW9yt.jpg","drameTypeVo":{"drameName":"drama","drameType":"TV"},"id":"10089","name":"Chocolate","score":7.7,"tagList":[{"id":8,"name":"Drama"}],"tagNameList":["Drama"],"upImgUrl":"https://img.rr.tv/head/20170323/o_1490274449176.png","upName":"Uriah Garden","year":2019},{"areaList":[{"id":61,"name":"America"}],"areaNameList":["America"],"category":1,"coverHorizontalUrl":"https://img.netpop.app/cover/20211109/1636445747242_3ea551574cb484b5050cc96f96ba141e65wtZ057IwpTI3j9adVPN6Qalf8.jpg","coverVerticalUrl":"https://img.netpop.app/cover/20211109/1636445729937_9283f654d39473dfa74991632a3fc429g4U2GkX5SoVGfL9iNdaRv4hFavu.jpg","drameTypeVo":{"drameName":"drama","drameType":"TV"},"id":"1004","name":"StarBeam Season 2","score":6.9,"tagList":[{"id":1,"name":"Action"},{"id":2,"name":"Adventure"},{"id":3,"name":"Anime"},{"id":5,"name":"Comedy"},{"id":9,"name":"Family"},{"id":10,"name":"Fantasy"},{"id":19,"name":"Sci-Fi"}],"tagNameList":["Action","Adventure","Anime","Comedy","Family","Fantasy","Sci-Fi"],"upImgUrl":"https://img.rr.tv/head/20161207/o_1481097470907.jpg","upName":"Dominic Fielding","year":2020},{"areaList":[{"id":61,"name":"America"}],"areaNameList":["America"],"category":1,"coverHorizontalUrl":"https://img.netpop.app/cover/20210928/1632798724819_d181d133318c3631b6dea53cb68e7768画板 1 拷贝 173.png","coverVerticalUrl":"https://img.netpop.app/cover/20211109/1636446126593_6f11cbdfd2bfef0f5c4c04b840a8e4barBnJbfgDNWSTvSg2Tkps1KS7wTH.jpg","drameTypeVo":{"drameName":"drama","drameType":"TV"},"id":"1007","name":"Chico Bon Bon: Monkey with a Tool Belt Season 1","score":6.2,"tagList":[{"id":3,"name":"Anime"},{"id":9,"name":"Family"}],"tagNameList":["Anime","Family"],"upImgUrl":"http://img.rr.tv/head/20200519/o_1589887620171.jpeg","upName":"Paul Caroline","year":2020},{"areaList":[{"id":61,"name":"America"}],"areaNameList":["America"],"category":1,"coverHorizontalUrl":"https://img.netpop.app/cover/20211109/1636445778469_3a856866226de0fd38db6ab8658c6b3bxsI8a4hRUb2Q8eDcnW0GBjCoFHY.jpg","coverVerticalUrl":"https://img.netpop.app/cover/20211109/1636445557958_529c9233ff069d786992884bbbc30144ijJruqW5r7YtxUfWHbcV49y8NJ8.jpg","drameTypeVo":{"drameName":"drama","drameType":"TV"},"id":"1003","name":"StarBeam Season 1","score":6.9,"tagList":[{"id":1,"name":"Action"},{"id":2,"name":"Adventure"},{"id":3,"name":"Anime"},{"id":5,"name":"Comedy"},{"id":9,"name":"Family"},{"id":10,"name":"Fantasy"},{"id":19,"name":"Sci-Fi"}],"tagNameList":["Action","Adventure","Anime","Comedy","Family","Fantasy","Sci-Fi"],"upImgUrl":"http://img.rr.tv/head/20200519/o_1589888603375.jpeg","upName":"Veromca Forster","year":2020},{"areaList":[{"id":61,"name":"America"}],"areaNameList":["America"],"category":1,"coverHorizontalUrl":"https://img.netpop.app/cover/20211109/1636445402668_acad10bb70de99c0a9c7243d41ed25f8xN9mw9I4JnnRMFTcHLFtnv5hDkH.jpg","coverVerticalUrl":"https://img.netpop.app/cover/20211109/1636445361724_ea4f8c913d38e96e1b6872e8f063e2c01P73hdMxOmxeWySMA8RDvmS1dQ4.jpg","drameTypeVo":{"drameName":"drama","drameType":"TV"},"id":"1001","name":"Spirit Riding Free: Riding Academy Season 1","score":7.2,"tagList":[{"id":1,"name":"Action"},{"id":2,"name":"Adventure"},{"id":3,"name":"Anime"},{"id":9,"name":"Family"}],"tagNameList":["Action","Adventure","Anime","Family"],"upImgUrl":"http://img.rr.tv/head/20200715/o_0062LtImgy1ggo612ib4fj30jg0jf45a.jpg","upName":"Venus Crane","year":2020},{"areaList":[{"id":61,"name":"America"}],"areaNameList":["America"],"category":1,"coverHorizontalUrl":"https://img.netpop.app/cover/20211111/1636625060975_eb0fdfb196dc19ce0ae7ab48b531a8d2奇哥·蹦蹦和他的工具箱 第二季.png","coverVerticalUrl":"https://img.netpop.app/cover/20211111/1636625040110_233ec1b2f82555e4ee0d19f317fc2b61奇哥·蹦蹦和他的工具箱 第二季.png","drameTypeVo":{"drameName":"drama","drameType":"TV"},"id":"1008","name":"Chico Bon Bon: Monkey with a Tool Belt Season 2","score":6.2,"tagList":[{"id":3,"name":"Anime"},{"id":9,"name":"Family"}],"tagNameList":["Anime","Family"],"upImgUrl":"http://img.rr.tv/head/20200715/o_006yP4Ebly1ge1ahum91bj30u00u0jwi.jpg","upName":"Giles John","year":2020},{"areaList":[{"id":53,"name":"South Korea"}],"areaNameList":["South Korea"],"category":1,"coverHorizontalUrl":"https://img.netpop.app/cover/20211229/1640760967304_4e968c31b431c924753c237b4dc3cd307BFAureSoVKzyOfHnNBWQ2wLB18.jpg","coverVerticalUrl":"https://img.netpop.app/cover/20211229/1640760972884_9d29213a13d8710662007c6fda2de357vbWwgQ796gS2nRotu8rSL4eu02.jpg","drameTypeVo":{"drameName":"drama","drameType":"TV"},"id":"10075","name":"Trap [Vietsub]","score":7.6,"tagList":[{"id":6,"name":"Crime"},{"id":8,"name":"Drama"},{"id":23,"name":"Thriller"}],"tagNameList":["Crime","Drama","Thriller"],"upImgUrl":"https://img.rr.tv/head/20161206/o_1481005397493.jpg","upName":"Omar Virginia","year":2019},{"areaList":[{"id":61,"name":"America"}],"areaNameList":["America"],"category":1,"coverHorizontalUrl":"https://img.netpop.app/cover/20210928/1632800033999_0746820c3a4e46cd69e45a3bf76ed30f画板 1 拷贝 163.png","coverVerticalUrl":"https://img.netpop.app/cover/20210831/o_1630388467822.jpg","drameTypeVo":{"drameName":"drama","drameType":"TV"},"id":"1000","name":"Glitch Techs Season 2","score":7.7,"tagList":[{"id":1,"name":"Action"},{"id":2,"name":"Adventure"},{"id":3,"name":"Anime"},{"id":5,"name":"Comedy"},{"id":9,"name":"Family"},{"id":19,"name":"Sci-Fi"},{"id":23,"name":"Thriller"}],"tagNameList":["Action","Adventure","Anime","Comedy","Family","Sci-Fi","Thriller"],"upImgUrl":"https://img.rr.tv/head/20180801/o_1533101911535.png","upName":"Moore Elsie","year":2020}],"name":"The Lord of the Rings: The Rings of Power Season 1","nameJson":"","refList":[],"reserved":false,"score":6.6,"seriesNo":null,"showSetName":false,"starList":[],"tagList":[{"id":1,"name":"Action"},{"id":2,"name":"Adventure"},{"id":8,"name":"Drama"},{"id":10,"name":"Fantasy"}],"tagNameList":["Action","Adventure","Drama","Fantasy"],"translateType":0,"upInfo":{"upId":100894,"upImgUrl":"http://img.rr.tv/head/20200715/o_0062LtImgy1ggkgnkyzhij30zk0zk0xb.jpg","upName":"Hamiltion Yonng"},"updateInfo":{"updatePeriod":",5","updateStatus":2},"year":2022},"sources":[{"quality":720,"url":"https://ali-cdn-play.loklok.tv/db6c5b6ef3454755aa3cac1326de703b/08d91d24c53d48c3b2fbe0c2b467ab96-b2243ef6050357f1bb6db98d11c62dbb-sd.m3u8?auth_key=1665196313-e6aa70a152a34057b8d0e25fe9e71ff1-0-fbd4f1cc72a8b5b0e8a64fbc9749cf00"},{"quality":540,"url":"https://ali-cdn-play.loklok.tv/db6c5b6ef3454755aa3cac1326de703b/08d91d24c53d48c3b2fbe0c2b467ab96-5c0d0d8b5a025f63a95b94ac6e4908fe-ld.m3u8?auth_key=1665196313-2893649635bc4303b639593944c116f6-0-02dc47077e43e2bdc4c69af01162b6f1"},{"quality":360,"url":"https://ali-cdn-play.loklok.tv/db6c5b6ef3454755aa3cac1326de703b/08d91d24c53d48c3b2fbe0c2b467ab96-e2d003433abc8e91b7a70364c6cd6a6e-fd.m3u8?auth_key=1665196313-9217710ab7b64230a372339b93cefbe3-0-0f1a3b5f14491fd480665cb4fbccdece"}],"subtitles":[{"language":"Tiếng Việt","url":"https://img.netpop.app/subtitles/20220902/1662087468135_the-lord-of-the-rings-the-rings-of-power-s01e01-1080p-web-h264-cakes_track44_-vie--srt","lang":"vi"},{"language":"English","url":"https://img.netpop.app/subtitles/20220902/1662087462539_the-lord-of-the-rings-the-rings-of-power-s01e01-1080p-web-h264-cakes_track4_-eng--srt","lang":"en"},{"language":"Bahasa Indonesia","url":"https://img.netpop.app/subtitles/20220902/1662087464546_the-lord-of-the-rings-the-rings-of-power-s01e01-1080p-web-h264-cakes_track24_-ind--srt","lang":"in_ID"},{"language":"Bahasa Melayu","url":"https://img.netpop.app/subtitles/20220902/1662087466115_the-lord-of-the-rings-the-rings-of-power-s01e01-1080p-web-h264-cakes_track30_-may--srt","lang":"ms"},{"language":"ภาษาไทย","url":"https://img.netpop.app/subtitles/20220902/1662087469801_the-lord-of-the-rings-the-rings-of-power-s01e01-1080p-web-h264-cakes_track41_-tha--srt","lang":"th"},{"language":"简体中文","url":"https://img.netpop.app/subtitles/20220902/1662087471305_the-lord-of-the-rings-the-rings-of-power-s01e01-1080p-web-h264-cakes_track8_-chi--srt","lang":"zh_CN"},{"language":"繁体中文","url":"https://img.netpop.app/subtitles/20220902/1662087473134_the-lord-of-the-rings-the-rings-of-power-s01e01-1080p-web-h264-cakes_track9_-chi--srt","lang":"zh_TW"},{"language":"عربي","url":"https://img.netpop.app/subtitles/20220902/1662087476189_the-lord-of-the-rings-the-rings-of-power-s01e01-1080p-web-h264-cakes_track5_-ara--srt","lang":"ar"},{"language":"فارسی (Auto)","url":"https://subtitles.netpop.app/subtitles/20220902/1662087571312_fa_1662087462539_the-lord-of-the-rings-the-rings-of-power-s01e01-1080p-web-h264-cakes_track4_-eng--srt","lang":"fa"},{"language":"Español","url":"https://img.netpop.app/subtitles/20220902/1662087479640_the-lord-of-the-rings-the-rings-of-power-s01e01-1080p-web-h264-cakes_track29_-spa--srt","lang":"es"},{"language":"português","url":"https://img.netpop.app/subtitles/20220902/1662087480456_the-lord-of-the-rings-the-rings-of-power-s01e01-1080p-web-h264-cakes_track35_-por--srt","lang":"pt"},{"language":"Türk","url":"https://img.netpop.app/subtitles/20220902/1662087482514_the-lord-of-the-rings-the-rings-of-power-s01e01-1080p-web-h264-cakes_track42_-tur--srt","lang":"tr"},{"language":"français","url":"https://img.netpop.app/subtitles/20220902/1662087484592_the-lord-of-the-rings-the-rings-of-power-s01e01-1080p-web-h264-cakes_track17_-fre--srt","lang":"fr"}]}},"__N_SSG":true}